<sv:node xmlns:sv="http://www.jcp.org/jcr/sv/1.0" xmlns:xsi="http://www.w3.org/2001/XMLSchema-instance" sv:name="how-minimize-pollen-allergic-reaction">
    <sv:property sv:name="jcr:primaryType" sv:type="Name">
        <sv:value>mgnl:page</sv:value>
    </sv:property>
    <sv:property sv:name="mgnl:template" sv:type="String">
        <sv:value>app:pages/one-column</sv:value>
    </sv:property>
    <sv:property sv:name="mgnl:activationStatus" sv:type="Boolean">
        <sv:value>false</sv:value>
    </sv:property>

    <sv:node sv:name="main-column">
        <sv:property sv:name="jcr:primaryType" sv:type="Name">
            <sv:value>mgnl:area</sv:value>
        </sv:property>
        <sv:node sv:name="0">
            <sv:property sv:name="jcr:primaryType" sv:type="Name">
                <sv:value>mgnl:component</sv:value>
            </sv:property>
            <sv:property sv:name="mgnl:template" sv:type="String">
                <sv:value>app:components/article</sv:value>
            </sv:property>
            <sv:property sv:name="title" sv:type="String">
                <sv:value>How can I minimize my allergic reaction to pollen?</sv:value>
            </sv:property>
            <sv:property sv:name="category" sv:type="String">
                <sv:value>Health</sv:value>
            </sv:property>
            <sv:property sv:name="body" sv:type="String">
                <sv:value>
                    <![CDATA[<p>Premedication with intranasal steroids and an antihistamine approximately two weeks before the start of the season is usually very helpful, and continuing that care for the balance will make a big difference. Also at those times, especially when your car is covered with pollen, wash the car, put on the air conditioner and drive with the windows closed.</p>]]>
                </sv:value>
            </sv:property>
        </sv:node>
    </sv:node>
</sv:node>